pyp333.py
pyp333-0.0.3.dist-info/METADATA
pyp333-0.0.3.dist-info/WHEEL
pyp333-0.0.3.dist-info/entry_points.txt
pyp333-0.0.3.dist-info/top_level.txt
pyp333-0.0.3.dist-info/RECORD
