Metadata-Version: 2.1
Name: pyp333
Version: 0.0.3
Summary: A package for pratice
Home-page: https://github.com/abcde117/233.git
Author: abcd1234
Author-email: s2122083@stu.muashino-u.ac.jp
License: UNKNOWN
Project-URL: Bug Tracker, https://github.com/abcde117/233.git
Platform: UNKNOWN
Classifier: Programming Language :: Python :: 3
Classifier: License :: OSI Approved :: MIT License
Classifier: Operating System :: OS Independent
Requires-Python: >=3.7
